Uebungspack 12/12_170/Schaltung.v
module schaltung(clk, a, b, c, d, e ,f);
    input clk;
    output a, b, c, d, e, f;
    reg a = 0;
    reg b = 0;
    reg c = 0;
    reg d = 0;
    reg e = 0;
    reg f = 0;

    reg z = 0; //zwischenspeicher, damit ich c mit dem alten b auswerten kann bevor ich dann b ändere

    // nonblocking
    always @(posedge clk) begin
        c <= b ;
        a <= (a^b^c); // ^ ist XOR Operator
        b <= (a^b^c) | c; // | ist OR Operator
    end

    //blocking
    always @(posedge clk) begin
        d = (d^e^f);
        z = d | f; //dadurch, dass der wert direkt in a geändert wird, brauche ich (a^b^c) kein zweites mal
        f = e;
        e = z;
    end
    
endmodule

Uebungspack 12/12_170/Testbench.v
module top_level;
    reg clk = 0, key;
    wire a, b, c, d, e, f;
    always #5 clk = !clk;

    schaltung S(clk, a, b, c, d, e, f);

    initial begin
        $dumpfile("gtk.vcd");
        $dumpvars(0, clk, a, b, c, d, e, f);
        //ich lasse monitor weg, da ich gtk wave benutze

        //startzustände
        #0 S.a = 0; S.b = 0; S.c = 0; S.d = 0; S.e = 0; S.f = 0;
        #10 S.a = 0; S.b = 0; S.c = 1; S.d = 0; S.e = 0; S.f = 1;
        #10 S.a = 0; S.b = 1; S.c = 0; S.d = 0; S.e = 1; S.f = 0;
        #10 S.a = 0; S.b = 1; S.c = 1; S.d = 0; S.e = 1; S.f = 1;
        #10 S.a = 1; S.b = 0; S.c = 0; S.d = 1; S.e = 0; S.f = 0;
        #10 S.a = 1; S.b = 0; S.c = 1; S.d = 1; S.e = 0; S.f = 1;
        #10 S.a = 1; S.b = 1; S.c = 0; S.d = 1; S.e = 1; S.f = 0;
        #10 S.a = 1; S.b = 1; S.c = 1; S.d = 1; S.e = 1; S.f = 1;
        #10 $finish;
    end
endmodule

Uebungspack 12/12_170/gtk.vcd
$date
	Thu May 29 21:38:31 2025
$end
$version
	Icarus Verilog
$end
$timescale
	1s
$end
$scope module top_level $end
$var reg 1 ! clk $end
$upscope $end
$scope module top_level $end
$var wire 1 " a $end
$upscope $end
$scope module top_level $end
$var wire 1 # b $end
$upscope $end
$scope module top_level $end
$var wire 1 $ c $end
$upscope $end
$scope module top_level $end
$var wire 1 % d $end
$upscope $end
$scope module top_level $end
$var wire 1 & e $end
$upscope $end
$scope module top_level $end
$var wire 1 ' f $end
$upscope $end
$enddefinitions $end
$comment Show the parameter values. $end
$dumpall
$end
#0
$dumpvars
0'
0&
0%
0$
0#
0"
0!
$end
#5
1!
#10
0!
1'
1$
#15
1#
1"
0$
1&
0'
1%
1!
#20
0!
0%
0"
#25
1"
1$
1'
1%
1!
#30
0!
0%
0"
#35
1!
#40
0!
0'
0&
1%
0$
0#
1"
#45
1#
1&
1!
#50
0!
1'
0&
1$
0#
#55
1#
0"
0$
1&
0'
0%
1!
#60
0!
1%
1"
#65
0#
0"
1$
0&
1'
0%
1!
#70
0!
1&
1%
1#
1"
