Verilog_Ali/Ampelschaltung.v
module top_level();
    reg clk = 0;
    reg g,y,r;
    always #1 clk = ~clk;         //knöpfe starten ja bei 1 hast du gemeint sollte aber
    reg [2:0] cnt;                // keinen Unterschied machen 
    reg [2:0] tk;                 // mit knopfdruch fange ich einfach ab wenn der knopf
    reg knopf  = 1;               // gedrückt wurde ausserhalb vom posedge 
    reg knopfdruck = 1;           // keine Ahnung wies einfacher geht maybe ohne posedge aber     
    always @(negedge knopf) begin // würde es ja nicht zünden wenn gerade keine taktänderun ist
        knopfdruck <= 0;
    end
    always @(posedge clk) begin 
        if (knopfdruck == 0 && cnt == 3'd6) begin
            tk <= tk + 1;
            if (tk == 3'd7) begin 
                r <= 1;
                y <= 0;
                g <= 0;
                $display ("HELOOOOOO");
                knopfdruck <= 1;
                cnt <= cnt + 3'd1;
                tk <= 3'd0;
            end
        end else cnt  <= cnt + 3'd1;
    end

    always @(clk) begin
        case (cnt)
            3'b111: begin
                r = 1;
                y = 1;
                g = 0;
            end
            3'd0, 3'd1: begin
                r = 0;
                y = 0;
                g = 1;
            end
            3'd2, 3'd3: begin
                r = 0;
                y = 1;
                g = 0;
            end
            default: begin
                r = 1;
                y = 0;
                g = 0;
            end
        endcase
        end
    
    // Testbench
    always 
        #2 $display("%4t %b    | %b | %b | %b  |   %b", $time , cnt ,g,y,r, knopfdruck);
    
    initial begin
        $dumpfile("testbench.vcd");
        $dumpvars(0, top_level);    
        $display("   T  cnt | g | y | r | knopfdruck |\n--------------------------------");
        cnt = 3'd0; tk = 3'd0; knopf = 1;
        #2 knopf = 0;
        #4 knopf = 1;
        #100 $finish;
    end
endmodule

Verilog_Ali/testbench.vcd
$date
	Thu Jun  5 12:35:40 2025
$end
$version
	Icarus Verilog
$end
$timescale
	1s
$end
$scope module top_level $end
$var reg 1 ! clk $end
$var reg 3 " cnt [2:0] $end
$var reg 1 # g $end
$var reg 1 $ knopf $end
$var reg 1 % knopfdruck $end
$var reg 1 & r $end
$var reg 3 ' tk [2:0] $end
$var reg 1 ( y $end
$upscope $end
$enddefinitions $end
$comment Show the parameter values. $end
$dumpall
$end
#0
$dumpvars
0(
b0 '
0&
1%
1$
1#
b0 "
0!
$end
#1
b1 "
1!
#2
0%
0!
0$
#3
b10 "
1!
#4
0#
1(
0!
#5
b11 "
1!
#6
0!
1$
#7
b100 "
1!
#8
0(
1&
0!
#9
b101 "
1!
#10
0!
#11
b110 "
1!
#12
0!
#13
b1 '
1!
#14
0!
#15
b10 '
1!
#16
0!
#17
b11 '
1!
#18
0!
#19
b100 '
1!
#20
0!
#21
b101 '
1!
#22
0!
#23
b110 '
1!
#24
0!
#25
b111 '
1!
#26
0!
#27
b111 "
1%
b0 '
1!
#28
1(
0!
#29
b0 "
1!
#30
1#
0(
0&
0!
#31
b1 "
1!
#32
0!
#33
b10 "
1!
#34
0#
1(
0!
#35
b11 "
1!
#36
0!
#37
b100 "
1!
#38
0(
1&
0!
#39
b101 "
1!
#40
0!
#41
b110 "
1!
#42
0!
#43
b111 "
1!
#44
1(
0!
#45
b0 "
1!
#46
1#
0(
0&
0!
#47
b1 "
1!
#48
0!
#49
b10 "
1!
#50
0#
1(
0!
#51
b11 "
1!
#52
0!
#53
b100 "
1!
#54
0(
1&
0!
#55
b101 "
1!
#56
0!
#57
b110 "
1!
#58
0!
#59
b111 "
1!
#60
1(
0!
#61
b0 "
1!
#62
1#
0(
0&
0!
#63
b1 "
1!
#64
0!
#65
b10 "
1!
#66
0#
1(
0!
#67
b11 "
1!
#68
0!
#69
b100 "
1!
#70
0(
1&
0!
#71
b101 "
1!
#72
0!
#73
b110 "
1!
#74
0!
#75
b111 "
1!
#76
1(
0!
#77
b0 "
1!
#78
1#
0(
0&
0!
#79
b1 "
1!
#80
0!
#81
b10 "
1!
#82
0#
1(
0!
#83
b11 "
1!
#84
0!
#85
b100 "
1!
#86
0(
1&
0!
#87
b101 "
1!
#88
0!
#89
b110 "
1!
#90
0!
#91
b111 "
1!
#92
1(
0!
#93
b0 "
1!
#94
1#
0(
0&
0!
#95
b1 "
1!
#96
0!
#97
b10 "
1!
#98
0#
1(
0!
#99
b11 "
1!
#100
0!
#101
b100 "
1!
#102
0(
1&
0!
#103
b101 "
1!
#104
0!
#105
b110 "
1!
