Uebungspack 12/12_173/mainPart3.v
module top_level();

    reg clk = 1;
    always #1 clk = !clk;

    reg[2:0] cnt = 0;       //erstelle 3 bit großen bus als counter
    always @(posedge clk) cnt = cnt + 1;

    wire red = 1, yellow = 1, green = 0;

    reg button = 0;

    always @(cnt == 0) button = ~button;

    always #1 $display("%b %f %b %b %b", clk, cnt, red, yellow, green);

    always @(cnt == 0 & ~button) begin
         // immer wenn sich count ändert aufrufen
        assign red <= (~cnt[0] & ~cnt[1] & ~cnt[2]) | (cnt[2] & (cnt[1] | cnt[0]));
        assign yellow <= (~cnt[2] & cnt[0] & cnt[1]) | (~cnt[0] & ~cnt[1] & ~cnt[2]) | (cnt[2] & ~cnt[0] & ~cnt[1]);
        assign green <= ~cnt[2] & ( cnt[1] & ~cnt[0] | ~cnt[1] & cnt[0]);
    end

    always @(cnt == 0 & button) begin
        assign red = 1;
        assign yellow = 0;
        assign green = 0;
    end

    initial begin
        $dumpfile("testbench.vcd"); 
        $dumpvars(0, clk, cnt, red, yellow, green, red2, yellow2, green2);
        #40 $finish;
    end

endmodule

Uebungspack 12/12_173/testbench.vcd
$date
	Thu Jun 05 00:44:08 2025
$end
$version
	Icarus Verilog
$end
$timescale
	1s
$end
$scope module top_level $end
$var reg 1 ! clk $end
$upscope $end
$scope module top_level $end
$var reg 3 " cnt [2:0] $end
$upscope $end
$scope module top_level $end
$var reg 1 # red $end
$upscope $end
$scope module top_level $end
$var reg 1 $ yellow $end
$upscope $end
$scope module top_level $end
$var reg 1 % green $end
$upscope $end
$scope module top_level $end
$var reg 1 & button $end
$upscope $end
$enddefinitions $end
$comment Show the parameter values. $end
$dumpall
$end
#0
$dumpvars
0&
0%
1$
1#
b0 "
1!
$end
#1
0!
#2
1%
0$
0#
b1 "
1!
#3
0!
#4
b10 "
1!
#5
0!
#6
0%
1$
b11 "
1!
#7
0!
#8
b100 "
1!
#9
0!
#10
0$
1#
b101 "
1!
1&
#11
0!
#12
b110 "
1!
#13
0!
#14
b111 "
1!
#15
0!
#16
0&
b0 "
1!
#17
0!
#18
b1 "
1!
#19
0!
#20
b10 "
1!
#21
0!
#22
b11 "
1!
#23
0!
#24
b100 "
1!
#25
0!
#26
b101 "
1!
#27
0!
#28
b110 "
1!
#29
0!
#30
b111 "
1!
#31
0!
#32
1$
b0 "
1!
#33
0!
#34
1%
0$
0#
b1 "
1!
#35
0!
#36
b10 "
1!
#37
0!
#38
0%
1$
b11 "
1!
#39
0!
#40
b100 "
1!
#41
0!
#42
0$
1#
b101 "
1!
#43
0!
#44
b110 "
1!
#45
0!
#46
b111 "
1!
#47
0!
#48
1$
b0 "
1!
#49
0!
#50
1%
0$
0#
b1 "
1!
#51
0!
#52
b10 "
1!
#53
0!
#54
0%
1$
b11 "
1!
#55
0!
#56
b100 "
1!
#57
0!
#58
0$
1#
b101 "
1!
#59
0!
#60
b110 "
1!
#61
0!
#62
b111 "
1!
#63
0!
#64
1$
b0 "
1!
#65
0!
#66
1%
0$
0#
b1 "
1!
#67
0!
#68
b10 "
1!
#69
0!
#70
0%
1$
b11 "
1!
